biosaur_src/__init__.py
biosaur_src/bio.py
biosaur_src/biosaur.py
biosaur_src/classes.py
biosaur_src/funcs.py
biosaur_src/utills.py
Biosaur-2.0.3.dist-info/LICENSE
Biosaur-2.0.3.dist-info/METADATA
Biosaur-2.0.3.dist-info/WHEEL
Biosaur-2.0.3.dist-info/entry_points.txt
Biosaur-2.0.3.dist-info/top_level.txt
Biosaur-2.0.3.dist-info/RECORD
